scientisttools/__init__.py
scientisttools/auto_cut_tree.py
scientisttools/ca.py
scientisttools/catdesc.py
scientisttools/catvarhca.py
scientisttools/cca.py
scientisttools/cmdscale.py
scientisttools/coeffLg.py
scientisttools/coeffRV.py
scientisttools/conditional_average.py
scientisttools/contdesc.py
scientisttools/covariance_to_correlation.py
scientisttools/datasets.py
scientisttools/dimdesc.py
scientisttools/efa.py
scientisttools/eigenvalue.py
scientisttools/eta2.py
scientisttools/famd.py
scientisttools/function_eta2.py
scientisttools/function_lg.py
scientisttools/fviz_ca.py
scientisttools/fviz_cca.py
scientisttools/fviz_cmdscale.py
scientisttools/fviz_contrib.py
scientisttools/fviz_corrcircle.py
scientisttools/fviz_corrplot.py
scientisttools/fviz_cos2.py
scientisttools/fviz_efa.py
scientisttools/fviz_famd.py
scientisttools/fviz_hcpc.py
scientisttools/fviz_mca.py
scientisttools/fviz_mds.py
scientisttools/fviz_mfa.py
scientisttools/fviz_mpca.py
scientisttools/fviz_partialpca.py
scientisttools/fviz_pca.py
scientisttools/fviz_pcamix.py
scientisttools/fviz_shepard.py
scientisttools/get_ca.py
scientisttools/get_efa.py
scientisttools/get_famd.py
scientisttools/get_mca.py
scientisttools/get_mds.py
scientisttools/get_melt.py
scientisttools/get_mfa.py
scientisttools/get_mpca.py
scientisttools/get_partialpca.py
scientisttools/get_pca.py
scientisttools/get_pcamix.py
scientisttools/gg_circle.py
scientisttools/hcpc.py
scientisttools/kmo.py
scientisttools/mca.py
scientisttools/mds.py
scientisttools/mfa.py
scientisttools/mfact.py
scientisttools/mfamix.py
scientisttools/mfaqual.py
scientisttools/mpca.py
scientisttools/partialcca.py
scientisttools/partialpca.py
scientisttools/pca.py
scientisttools/pcamix.py
scientisttools/quali_var_desc.py
scientisttools/quanti_var_desc.py
scientisttools/recodecat.py
scientisttools/recodecont.py
scientisttools/recodevar.py
scientisttools/recodevarfamd.py
scientisttools/reconst.py
scientisttools/revaluate_cat_variable.py
scientisttools/sim_dist.py
scientisttools-0.1.6.dist-info/LICENSE.txt
scientisttools-0.1.6.dist-info/METADATA
scientisttools-0.1.6.dist-info/WHEEL
scientisttools-0.1.6.dist-info/top_level.txt
scientisttools-0.1.6.dist-info/RECORD
