Metadata-Version: 2.1
Name: scientisttools
Version: 0.1.6
Summary: Python library for multidimensional analysis, classification - clustering analysis and multidimensional analysis
Author: Duverier DJIFACK ZEBAZE
Author-email: djifacklab@gmail.com
Classifier: Programming Language :: Python :: 3
Classifier: License :: OSI Approved :: MIT License
Classifier: Operating System :: OS Independent
Requires-Python: >=3.10
License-File: LICENSE.txt
Requires-Dist: numpy (>=1.26.4)
Requires-Dist: matplotlib (>=3.8.4)
Requires-Dist: scikit-learn (>=1.2.2)
Requires-Dist: pandas (>=2.2.2)
Requires-Dist: polars (>=0.19.2)
Requires-Dist: mapply (>=0.1.21)
Requires-Dist: plotnine (>=0.10.1)
Requires-Dist: pingouin (>=0.5.4)
Requires-Dist: scientistmetrics (>=0.0.4)
